algorithms/__init__.py
algorithms/algorithm.py
algorithms/iaggregator.py
algorithms/iclassifier.py
algorithms/iclustering.py
algorithms/idescriptor.py
algorithms/idetector.py
algorithms/idistance.py
algorithms/ipoints_detector.py
algorithms/ipreprocessor.py
algorithms/iquality_estimator.py
algorithms/itracker.py
mnd_algorithms-0.1.0.dist-info/LICENSE
mnd_algorithms-0.1.0.dist-info/METADATA
mnd_algorithms-0.1.0.dist-info/WHEEL
mnd_algorithms-0.1.0.dist-info/top_level.txt
mnd_algorithms-0.1.0.dist-info/RECORD
