Metadata-Version: 2.1
Name: mnd-algorithms
Version: 0.1.0
Summary: Provides some interfaces for common algorithms used mainly in image and video processing.
Home-page: https://github.com/mnicolas94/algorithms
Author: Miguel Nicolás-Díaz
Author-email: miguelcok27@gmail.com
License: UNKNOWN
Platform: UNKNOWN
Classifier: Programming Language :: Python :: 3
Classifier: License :: OSI Approved :: MIT License
Classifier: Operating System :: OS Independent
Classifier: Development Status :: 3 - Alpha
Classifier: Intended Audience :: Developers
Requires-Python: >=3.6
License-File: LICENSE
Requires-Dist: propsettings
